kotodama/__init__.py
kotodama/kotodama.py
kotodama/data/kotodama_dic.csv
kotodama-0.0.18.dist-info/LICENSE.txt
kotodama-0.0.18.dist-info/METADATA
kotodama-0.0.18.dist-info/WHEEL
kotodama-0.0.18.dist-info/top_level.txt
kotodama-0.0.18.dist-info/RECORD
