Metadata-Version: 2.1
Name: kotodama
Version: 0.0.18
Summary: 日本語の動詞を活用形に変換する
Home-page: UNKNOWN
Author: Yoshiki Ohira
Author-email: ohira.yoshiki@irl.sys.es.osaka-u.ac.jp
License: UNKNOWN
Platform: UNKNOWN
Classifier: Programming Language :: Python :: 3
Classifier: License :: OSI Approved :: MIT License
Classifier: Operating System :: OS Independent
